MANIFEST.in
README.md
setup.py
django_mp_suppliers.egg-info/PKG-INFO
django_mp_suppliers.egg-info/SOURCES.txt
django_mp_suppliers.egg-info/dependency_links.txt
django_mp_suppliers.egg-info/top_level.txt
supplier_products/__init__.py
supplier_products/admin.py
supplier_products/email.py
supplier_products/forms.py
supplier_products/managers.py
supplier_products/models.py
supplier_products/querysets.py
supplier_products/tasks.py
supplier_products/urls.py
supplier_products/views.py
supplier_products/locale/uk/LC_MESSAGES/django.mo
supplier_products/locale/uk/LC_MESSAGES/django.po
supplier_products/migrations/0001_initial.py
supplier_products/migrations/0002_auto_20201007_1937.py
supplier_products/migrations/__init__.py
suppliers/__init__.py
suppliers/actions.py
suppliers/admin.py
suppliers/forms.py
suppliers/models.py
suppliers/locale/uk/LC_MESSAGES/django.mo
suppliers/locale/uk/LC_MESSAGES/django.po
suppliers/migrations/0001_initial.py
suppliers/migrations/0002_supplier_order_alter_supplier_id_and_more.py
suppliers/migrations/0003_default_supplier_order.py
suppliers/migrations/__init__.py