Metadata-Version: 2.1
Name: django-mp-suppliers
Version: 1.0.1
Summary: Django suppliers app
Home-page: https://github.com/pmaigutyak/mp-suppliers
Download-URL: https://github.com/pmaigutyak/mp-suppliers/archive/1.0.1.tar.gz
Author: Paul Maigutyak
Author-email: pmaigutyak@gmail.com
License: MIT
